pylons_sphinx_themes/__init__.py
pylons_sphinx_themes/pylons_theme_support.py
pylons_sphinx_themes/pylons/layout.html
pylons_sphinx_themes/pylons/theme.conf
pylons_sphinx_themes/pylons/static/dialog-note.png
pylons_sphinx_themes/pylons/static/dialog-seealso.png
pylons_sphinx_themes/pylons/static/dialog-topic.png
pylons_sphinx_themes/pylons/static/dialog-warning.png
pylons_sphinx_themes/pylons/static/edit-me-on-github.png
pylons_sphinx_themes/pylons/static/epub.css
pylons_sphinx_themes/pylons/static/footerbg.png
pylons_sphinx_themes/pylons/static/headerbg.png
pylons_sphinx_themes/pylons/static/ie6.css
pylons_sphinx_themes/pylons/static/in_progress.png
pylons_sphinx_themes/pylons/static/middlebg.png
pylons_sphinx_themes/pylons/static/outdated.png
pylons_sphinx_themes/pylons/static/pylons-latex.png
pylons_sphinx_themes/pylons/static/pylons-small.png
pylons_sphinx_themes/pylons/static/pylons.css_t
pylons_sphinx_themes/pylons/static/pylons.ico
pylons_sphinx_themes/pylons/static/pylons.png
pylons_sphinx_themes/pylons/static/transparent.gif
pylons_sphinx_themes/pylonsfw/theme.conf
pylons_sphinx_themes/pylonsfw/static/pylons.ico
pylons_sphinx_themes/pylonsfw/static/pylonsfw-small.png
pylons_sphinx_themes/pyramid/theme.conf
pylons_sphinx_themes/pyramid/static/pyramid-latex.png
pylons_sphinx_themes/pyramid/static/pyramid-small.png
pylons_sphinx_themes/pyramid/static/pyramid.ico
pylons_sphinx_themes/pyramid/static/pyramid.png
pylons_sphinx_themes-1.0.6.dist-info/DESCRIPTION.rst
pylons_sphinx_themes-1.0.6.dist-info/METADATA
pylons_sphinx_themes-1.0.6.dist-info/RECORD
pylons_sphinx_themes-1.0.6.dist-info/WHEEL
pylons_sphinx_themes-1.0.6.dist-info/metadata.json
pylons_sphinx_themes-1.0.6.dist-info/top_level.txt
